[{
        "viajes_h_por_vivienda": 0.2,
        "transporte_privado": 0.1,
        "transporte_publico": 0.036,
        "peatones_viajes": 0.036,
        "ciclos_viajes": 0.008
    },
    {
        "viajes_h_por_vivienda": 0.2,
        "transporte_privado": 0.1,
        "transporte_publico": 0.036,
        "peatones_viajes": 0.036,
        "ciclos_viajes": 0.008
    },
    {
        "viajes_h_por_vivienda": 1,
        "transporte_privado": 0.5,
        "transporte_publico": 0.18,
        "peatones_viajes": 0.18,
        "ciclos_viajes": 0.04
    },
    {
        "viajes_h_por_vivienda": 0.2,
        "transporte_privado": 0.1,
        "transporte_publico": 0.036,
        "peatones_viajes": 0.036,
        "ciclos_viajes": 0.008
    },
    {
        "viajes_h_por_vivienda": 0.2,
        "transporte_privado": 0.1,
        "transporte_publico": 0.036,
        "peatones_viajes": 0.036,
        "ciclos_viajes": 0.008
    }

]